libcrypto_c_exports.dll
crypto_cpp_py/__init__.py
crypto_cpp_py/cpp_bindings.py
crypto_cpp_py/utils.py
crypto_cpp_py-1.4.5.dist-info/METADATA
crypto_cpp_py-1.4.5.dist-info/WHEEL
crypto_cpp_py-1.4.5.dist-info/top_level.txt
crypto_cpp_py-1.4.5.dist-info/RECORD
