Metadata-Version: 2.1
Name: crypto_cpp_py
Version: 1.4.5
Summary: This is a packaged crypto-cpp program
Home-page: https://github.com/software-mansion-labs/crypto-cpp-py.git
Author: Wojciech Szymczyk, Marcin Warchoł, Kamil Jankowski
Author-email: wojciech.szymczyk@swmansion.com, marcin.warchol@swmansion.com, kamil.jankowski@swmansion.com
License: UNKNOWN
Platform: UNKNOWN
Requires-Python: >=3.8
Provides-Extra: build
